[{"timestamp":"2025-12-26T01:24:28.639Z","count":0,"uniques":0},{"timestamp":"2025-12-27T01:22:28.317Z","count":0,"uniques":0},{"timestamp":"2025-12-28T01:42:52.957Z","count":0,"uniques":0},{"timestamp":"2025-12-29T01:41:16.659Z","count":0,"uniques":0},{"timestamp":"2025-12-30T01:24:54.218Z","count":0,"uniques":0},{"timestamp":"2025-12-31T01:25:52.715Z","count":0,"uniques":0},{"timestamp":"2026-01-01T00:00:00.000Z","count":1,"uniques":1},{"timestamp":"2026-01-02T01:26:23.931Z","count":0,"uniques":0},{"timestamp":"2026-01-03T01:21:50.058Z","count":0,"uniques":0},{"timestamp":"2026-01-04T01:43:53.645Z","count":0,"uniques":0},{"timestamp":"2026-01-05T01:44:00.702Z","count":0,"uniques":0},{"timestamp":"2026-01-06T01:26:20.253Z","count":0,"uniques":0},{"timestamp":"2026-01-07T01:26:30.028Z","count":0,"uniques":0},{"timestamp":"2026-01-08T01:27:09.655Z","count":0,"uniques":0},{"timestamp":"2026-01-09T01:27:19.194Z","count":0,"uniques":0},{"timestamp":"2026-01-10T01:24:33.222Z","count":0,"uniques":0},{"timestamp":"2026-01-11T01:43:52.879Z","count":0,"uniques":0},{"timestamp":"2026-01-12T01:40:41.460Z","count":0,"uniques":0},{"timestamp":"2026-01-13T01:23:38.192Z","count":0,"uniques":0},{"timestamp":"2026-01-14T01:39:42.174Z","count":0,"uniques":0},{"timestamp":"2026-01-15T01:25:33.499Z","count":0,"uniques":0},{"timestamp":"2026-01-16T01:27:39.433Z","count":0,"uniques":0},{"timestamp":"2026-01-17T01:23:44.776Z","count":0,"uniques":0},{"timestamp":"2026-01-18T01:42:40.173Z","count":0,"uniques":0},{"timestamp":"2026-01-19T01:41:35.052Z","count":0,"uniques":0},{"timestamp":"2026-01-20T01:26:47.797Z","count":0,"uniques":0},{"timestamp":"2026-01-21T01:39:38.818Z","count":0,"uniques":0},{"timestamp":"2026-01-22T01:39:12.319Z","count":0,"uniques":0},{"timestamp":"2026-01-23T01:27:14.428Z","count":0,"uniques":0},{"timestamp":"2026-01-24T01:25:03.965Z","count":0,"uniques":0},{"timestamp":"2026-01-25T01:45:43.245Z","count":0,"uniques":0}]
