[{"timestamp":"2022-12-15T01:05:27.876Z","count":0,"uniques":0},{"timestamp":"2022-12-16T01:00:24.378Z","count":0,"uniques":0},{"timestamp":"2022-12-17T00:58:43.335Z","count":0,"uniques":0},{"timestamp":"2022-12-18T01:00:39.449Z","count":0,"uniques":0},{"timestamp":"2022-12-19T00:58:34.199Z","count":0,"uniques":0},{"timestamp":"2022-12-20T01:03:27.201Z","count":0,"uniques":0},{"timestamp":"2022-12-21T00:58:34.662Z","count":0,"uniques":0},{"timestamp":"2022-12-22T01:01:26.889Z","count":0,"uniques":0},{"timestamp":"2022-12-23T00:59:40.522Z","count":0,"uniques":0},{"timestamp":"2022-12-24T00:55:42.878Z","count":0,"uniques":0},{"timestamp":"2022-12-25T01:03:26.396Z","count":0,"uniques":0},{"timestamp":"2022-12-26T00:00:00.000Z","count":2,"uniques":1},{"timestamp":"2022-12-27T01:00:53.058Z","count":0,"uniques":0},{"timestamp":"2022-12-28T00:59:58.760Z","count":0,"uniques":0},{"timestamp":"2022-12-29T01:01:52.090Z","count":0,"uniques":0},{"timestamp":"2022-12-30T01:01:51.889Z","count":0,"uniques":0},{"timestamp":"2022-12-31T00:59:51.129Z","count":0,"uniques":0},{"timestamp":"2023-01-01T01:10:33.368Z","count":0,"uniques":0},{"timestamp":"2023-01-02T01:01:16.640Z","count":0,"uniques":0},{"timestamp":"2023-01-03T01:00:12.899Z","count":0,"uniques":0},{"timestamp":"2023-01-04T01:02:09.311Z","count":0,"uniques":0},{"timestamp":"2023-01-05T01:03:45.621Z","count":0,"uniques":0},{"timestamp":"2023-01-06T01:04:01.643Z","count":0,"uniques":0},{"timestamp":"2023-01-07T01:00:56.966Z","count":0,"uniques":0},{"timestamp":"2023-01-08T01:06:22.154Z","count":0,"uniques":0},{"timestamp":"2023-01-09T01:01:36.542Z","count":0,"uniques":0},{"timestamp":"2023-01-10T01:05:33.707Z","count":0,"uniques":0},{"timestamp":"2023-01-11T01:03:39.206Z","count":0,"uniques":0},{"timestamp":"2023-01-12T01:04:04.971Z","count":0,"uniques":0},{"timestamp":"2023-01-13T01:04:24.931Z","count":0,"uniques":0},{"timestamp":"2023-01-14T00:59:30.851Z","count":0,"uniques":0}]
