[{"timestamp":"2024-06-21T00:57:48.101Z","count":0,"uniques":0},{"timestamp":"2024-06-22T00:57:21.419Z","count":0,"uniques":0},{"timestamp":"2024-06-23T01:02:07.749Z","count":0,"uniques":0},{"timestamp":"2024-06-24T00:59:43.726Z","count":0,"uniques":0},{"timestamp":"2024-06-25T00:58:20.495Z","count":0,"uniques":0},{"timestamp":"2024-06-26T00:58:35.742Z","count":0,"uniques":0},{"timestamp":"2024-06-27T00:58:36.008Z","count":0,"uniques":0},{"timestamp":"2024-06-28T00:58:42.706Z","count":0,"uniques":0},{"timestamp":"2024-06-29T00:57:36.627Z","count":0,"uniques":0},{"timestamp":"2024-06-30T01:03:46.434Z","count":0,"uniques":0},{"timestamp":"2024-07-01T01:05:29.155Z","count":0,"uniques":0},{"timestamp":"2024-07-02T00:59:08.898Z","count":0,"uniques":0},{"timestamp":"2024-07-03T00:58:54.684Z","count":0,"uniques":0},{"timestamp":"2024-07-04T00:59:05.788Z","count":0,"uniques":0},{"timestamp":"2024-07-05T00:58:42.711Z","count":0,"uniques":0},{"timestamp":"2024-07-06T00:57:27.208Z","count":0,"uniques":0},{"timestamp":"2024-07-07T01:04:22.166Z","count":0,"uniques":0},{"timestamp":"2024-07-08T01:01:00.873Z","count":0,"uniques":0},{"timestamp":"2024-07-09T00:59:53.070Z","count":0,"uniques":0},{"timestamp":"2024-07-10T01:00:21.110Z","count":0,"uniques":0},{"timestamp":"2024-07-11T01:00:42.939Z","count":0,"uniques":0},{"timestamp":"2024-07-12T00:59:20.835Z","count":0,"uniques":0},{"timestamp":"2024-07-13T01:00:11.850Z","count":0,"uniques":0},{"timestamp":"2024-07-14T01:05:08.854Z","count":0,"uniques":0},{"timestamp":"2024-07-15T01:02:04.677Z","count":0,"uniques":0},{"timestamp":"2024-07-16T01:01:10.392Z","count":0,"uniques":0},{"timestamp":"2024-07-17T01:00:37.810Z","count":0,"uniques":0},{"timestamp":"2024-07-18T00:59:27.182Z","count":0,"uniques":0},{"timestamp":"2024-07-19T03:34:21.322Z","count":0,"uniques":0},{"timestamp":"2024-07-20T00:59:07.421Z","count":0,"uniques":0},{"timestamp":"2024-07-21T01:05:00.787Z","count":0,"uniques":0},{"timestamp":"2024-07-22T01:02:33.718Z","count":0,"uniques":0},{"timestamp":"2024-07-23T01:00:48.807Z","count":0,"uniques":0},{"timestamp":"2024-07-24T01:01:15.869Z","count":0,"uniques":0},{"timestamp":"2024-07-25T01:00:41.922Z","count":0,"uniques":0},{"timestamp":"2024-07-26T01:00:05.228Z","count":0,"uniques":0},{"timestamp":"2024-07-27T00:59:35.173Z","count":0,"uniques":0},{"timestamp":"2024-07-28T01:05:14.617Z","count":0,"uniques":0},{"timestamp":"2024-07-29T01:02:25.409Z","count":0,"uniques":0},{"timestamp":"2024-07-30T01:00:41.826Z","count":0,"uniques":0},{"timestamp":"2024-07-31T00:50:45.031Z","count":0,"uniques":0},{"timestamp":"2024-08-01T01:06:05.316Z","count":0,"uniques":0},{"timestamp":"2024-08-02T01:00:37.258Z","count":0,"uniques":0},{"timestamp":"2024-08-03T01:00:12.277Z","count":0,"uniques":0},{"timestamp":"2024-08-04T01:05:32.066Z","count":0,"uniques":0},{"timestamp":"2024-08-05T01:02:52.318Z","count":0,"uniques":0},{"timestamp":"2024-08-06T01:01:06.551Z","count":0,"uniques":0},{"timestamp":"2024-08-07T01:01:54.244Z","count":0,"uniques":0},{"timestamp":"2024-08-08T01:01:35.575Z","count":0,"uniques":0},{"timestamp":"2024-08-09T01:02:37.601Z","count":0,"uniques":0},{"timestamp":"2024-08-10T01:01:54.081Z","count":0,"uniques":0},{"timestamp":"2024-08-11T01:06:37.282Z","count":0,"uniques":0},{"timestamp":"2024-08-12T01:03:34.477Z","count":0,"uniques":0},{"timestamp":"2024-08-13T01:02:54.195Z","count":0,"uniques":0},{"timestamp":"2024-08-14T01:02:04.323Z","count":0,"uniques":0},{"timestamp":"2024-08-15T00:59:02.092Z","count":0,"uniques":0},{"timestamp":"2024-08-16T01:01:24.502Z","count":0,"uniques":0},{"timestamp":"2024-08-17T00:59:35.371Z","count":0,"uniques":0},{"timestamp":"2024-08-18T01:05:26.250Z","count":0,"uniques":0},{"timestamp":"2024-08-19T01:02:35.466Z","count":0,"uniques":0},{"timestamp":"2024-08-20T01:01:19.226Z","count":0,"uniques":0},{"timestamp":"2024-08-21T01:01:21.855Z","count":0,"uniques":0},{"timestamp":"2024-08-22T01:03:02.071Z","count":0,"uniques":0},{"timestamp":"2024-08-23T01:02:05.717Z","count":0,"uniques":0},{"timestamp":"2024-08-24T01:00:39.773Z","count":0,"uniques":0},{"timestamp":"2024-08-25T01:07:11.412Z","count":0,"uniques":0},{"timestamp":"2024-08-26T01:02:38.649Z","count":0,"uniques":0},{"timestamp":"2024-08-27T01:03:08.830Z","count":0,"uniques":0},{"timestamp":"2024-08-28T01:03:37.401Z","count":0,"uniques":0},{"timestamp":"2024-08-29T00:00:00.000Z","count":1,"uniques":1},{"timestamp":"2024-08-30T01:04:25.961Z","count":0,"uniques":0},{"timestamp":"2024-08-31T01:04:07.129Z","count":0,"uniques":0},{"timestamp":"2024-09-01T01:14:40.420Z","count":0,"uniques":0},{"timestamp":"2024-09-02T01:05:45.243Z","count":0,"uniques":0},{"timestamp":"2024-09-03T01:03:54.272Z","count":0,"uniques":0},{"timestamp":"2024-09-04T01:04:50.557Z","count":0,"uniques":0},{"timestamp":"2024-09-05T01:04:46.203Z","count":0,"uniques":0},{"timestamp":"2024-09-06T01:04:42.023Z","count":0,"uniques":0},{"timestamp":"2024-09-07T01:03:41.405Z","count":0,"uniques":0},{"timestamp":"2024-09-08T01:10:10.663Z","count":0,"uniques":0},{"timestamp":"2024-09-09T01:06:59.686Z","count":0,"uniques":0},{"timestamp":"2024-09-10T00:00:00.000Z","count":1,"uniques":1},{"timestamp":"2024-09-11T01:05:12.435Z","count":0,"uniques":0},{"timestamp":"2024-09-12T01:05:10.209Z","count":0,"uniques":0},{"timestamp":"2024-09-13T01:05:13.052Z","count":0,"uniques":0},{"timestamp":"2024-09-14T01:04:36.391Z","count":0,"uniques":0},{"timestamp":"2024-09-15T01:12:50.414Z","count":0,"uniques":0},{"timestamp":"2024-09-16T01:09:47.886Z","count":0,"uniques":0},{"timestamp":"2024-09-17T00:54:53.466Z","count":0,"uniques":0},{"timestamp":"2024-09-18T01:05:17.153Z","count":0,"uniques":0},{"timestamp":"2024-09-19T01:06:26.739Z","count":0,"uniques":0},{"timestamp":"2024-09-20T01:06:27.815Z","count":0,"uniques":0},{"timestamp":"2024-09-21T01:05:26.302Z","count":0,"uniques":0},{"timestamp":"2024-09-22T01:12:59.332Z","count":0,"uniques":0},{"timestamp":"2024-09-23T01:08:39.559Z","count":0,"uniques":0},{"timestamp":"2024-09-24T01:08:55.751Z","count":0,"uniques":0},{"timestamp":"2024-09-25T01:09:44.647Z","count":0,"uniques":0},{"timestamp":"2024-09-26T01:08:09.876Z","count":0,"uniques":0},{"timestamp":"2024-09-27T01:08:30.726Z","count":0,"uniques":0},{"timestamp":"2024-09-28T00:00:00.000Z","count":1,"uniques":1},{"timestamp":"2024-09-29T01:14:00.043Z","count":0,"uniques":0},{"timestamp":"2024-09-30T01:10:52.853Z","count":0,"uniques":0},{"timestamp":"2024-10-01T01:15:00.137Z","count":0,"uniques":0},{"timestamp":"2024-10-02T01:08:40.397Z","count":0,"uniques":0},{"timestamp":"2024-10-03T01:08:51.252Z","count":0,"uniques":0},{"timestamp":"2024-10-04T01:08:38.304Z","count":0,"uniques":0},{"timestamp":"2024-10-05T01:07:37.944Z","count":0,"uniques":0},{"timestamp":"2024-10-06T01:13:31.997Z","count":0,"uniques":0},{"timestamp":"2024-10-07T01:10:45.814Z","count":0,"uniques":0},{"timestamp":"2024-10-08T01:08:38.595Z","count":0,"uniques":0},{"timestamp":"2024-10-09T01:08:08.095Z","count":0,"uniques":0},{"timestamp":"2024-10-10T01:08:10.198Z","count":0,"uniques":0},{"timestamp":"2024-10-11T01:08:25.039Z","count":0,"uniques":0},{"timestamp":"2024-10-12T01:06:48.470Z","count":0,"uniques":0},{"timestamp":"2024-10-13T01:13:23.680Z","count":0,"uniques":0},{"timestamp":"2024-10-14T01:10:41.357Z","count":0,"uniques":0},{"timestamp":"2024-10-15T01:09:42.001Z","count":0,"uniques":0},{"timestamp":"2024-10-16T01:09:42.227Z","count":0,"uniques":0},{"timestamp":"2024-10-17T01:08:52.814Z","count":0,"uniques":0},{"timestamp":"2024-10-18T01:09:02.798Z","count":0,"uniques":0},{"timestamp":"2024-10-19T01:08:13.135Z","count":0,"uniques":0},{"timestamp":"2024-10-20T01:14:38.923Z","count":0,"uniques":0},{"timestamp":"2024-10-21T01:10:53.227Z","count":0,"uniques":0},{"timestamp":"2024-10-22T01:09:52.067Z","count":0,"uniques":0},{"timestamp":"2024-10-23T01:08:43.250Z","count":0,"uniques":0},{"timestamp":"2024-10-24T01:08:58.286Z","count":0,"uniques":0},{"timestamp":"2024-10-25T01:09:40.859Z","count":0,"uniques":0},{"timestamp":"2024-10-26T01:07:19.039Z","count":0,"uniques":0},{"timestamp":"2024-10-27T01:14:12.278Z","count":0,"uniques":0},{"timestamp":"2024-10-28T01:11:59.827Z","count":0,"uniques":0},{"timestamp":"2024-10-29T01:10:43.130Z","count":0,"uniques":0},{"timestamp":"2024-10-30T01:09:50.064Z","count":0,"uniques":0},{"timestamp":"2024-10-31T01:10:22.404Z","count":0,"uniques":0},{"timestamp":"2024-11-01T01:14:44.420Z","count":0,"uniques":0},{"timestamp":"2024-11-02T01:08:03.708Z","count":0,"uniques":0},{"timestamp":"2024-11-03T01:13:51.986Z","count":0,"uniques":0},{"timestamp":"2024-11-04T01:11:04.072Z","count":0,"uniques":0},{"timestamp":"2024-11-05T01:07:52.768Z","count":0,"uniques":0},{"timestamp":"2024-11-06T01:07:39.475Z","count":0,"uniques":0},{"timestamp":"2024-11-07T01:08:09.567Z","count":0,"uniques":0},{"timestamp":"2024-11-08T01:08:00.282Z","count":0,"uniques":0},{"timestamp":"2024-11-09T01:05:59.270Z","count":0,"uniques":0},{"timestamp":"2024-11-10T01:12:22.797Z","count":0,"uniques":0},{"timestamp":"2024-11-11T01:09:34.060Z","count":0,"uniques":0},{"timestamp":"2024-11-12T01:07:04.156Z","count":0,"uniques":0},{"timestamp":"2024-11-13T01:08:39.438Z","count":0,"uniques":0},{"timestamp":"2024-11-14T01:08:34.181Z","count":0,"uniques":0},{"timestamp":"2024-11-15T01:13:08.206Z","count":0,"uniques":0},{"timestamp":"2024-11-16T01:11:20.057Z","count":0,"uniques":0},{"timestamp":"2024-11-17T01:16:27.619Z","count":0,"uniques":0},{"timestamp":"2024-11-18T01:14:09.566Z","count":0,"uniques":0},{"timestamp":"2024-11-19T01:12:52.050Z","count":0,"uniques":0},{"timestamp":"2024-11-20T01:12:09.119Z","count":0,"uniques":0},{"timestamp":"2024-11-21T01:12:07.971Z","count":0,"uniques":0},{"timestamp":"2024-11-22T01:12:55.245Z","count":0,"uniques":0},{"timestamp":"2024-11-23T01:10:18.691Z","count":0,"uniques":0},{"timestamp":"2024-11-24T01:17:05.566Z","count":0,"uniques":0},{"timestamp":"2024-11-25T01:13:57.883Z","count":0,"uniques":0},{"timestamp":"2024-11-26T01:13:11.500Z","count":0,"uniques":0},{"timestamp":"2024-11-27T01:14:42.987Z","count":0,"uniques":0},{"timestamp":"2024-11-28T01:14:08.007Z","count":0,"uniques":0},{"timestamp":"2024-11-29T01:13:54.313Z","count":0,"uniques":0},{"timestamp":"2024-11-30T01:12:07.314Z","count":0,"uniques":0},{"timestamp":"2024-12-01T01:25:34.062Z","count":0,"uniques":0},{"timestamp":"2024-12-02T01:16:33.035Z","count":0,"uniques":0},{"timestamp":"2024-12-03T01:15:39.524Z","count":0,"uniques":0},{"timestamp":"2024-12-04T01:15:39.820Z","count":0,"uniques":0},{"timestamp":"2024-12-05T01:15:36.115Z","count":0,"uniques":0},{"timestamp":"2024-12-06T01:14:48.476Z","count":0,"uniques":0},{"timestamp":"2024-12-07T01:14:18.282Z","count":0,"uniques":0},{"timestamp":"2024-12-08T01:20:44.768Z","count":0,"uniques":0},{"timestamp":"2024-12-09T01:17:33.124Z","count":0,"uniques":0},{"timestamp":"2024-12-10T01:16:29.917Z","count":0,"uniques":0},{"timestamp":"2024-12-11T01:15:25.293Z","count":0,"uniques":0},{"timestamp":"2024-12-12T01:15:04.982Z","count":0,"uniques":0},{"timestamp":"2024-12-13T01:16:21.908Z","count":0,"uniques":0},{"timestamp":"2024-12-14T01:13:11.913Z","count":0,"uniques":0},{"timestamp":"2024-12-15T01:20:30.248Z","count":0,"uniques":0},{"timestamp":"2024-12-16T01:17:55.383Z","count":0,"uniques":0},{"timestamp":"2024-12-17T01:15:21.179Z","count":0,"uniques":0},{"timestamp":"2024-12-18T01:12:22.944Z","count":0,"uniques":0},{"timestamp":"2024-12-19T01:13:14.965Z","count":0,"uniques":0},{"timestamp":"2024-12-20T01:09:34.415Z","count":0,"uniques":0},{"timestamp":"2024-12-21T01:08:15.915Z","count":0,"uniques":0},{"timestamp":"2024-12-22T01:14:48.383Z","count":0,"uniques":0},{"timestamp":"2024-12-23T01:10:47.209Z","count":0,"uniques":0},{"timestamp":"2024-12-24T01:09:17.576Z","count":0,"uniques":0},{"timestamp":"2024-12-25T01:08:26.625Z","count":0,"uniques":0},{"timestamp":"2024-12-26T01:08:42.660Z","count":0,"uniques":0},{"timestamp":"2024-12-27T01:09:09.493Z","count":0,"uniques":0},{"timestamp":"2024-12-28T01:07:36.927Z","count":0,"uniques":0},{"timestamp":"2024-12-29T01:15:27.940Z","count":0,"uniques":0},{"timestamp":"2024-12-30T01:11:24.410Z","count":0,"uniques":0},{"timestamp":"2024-12-31T01:08:55.553Z","count":0,"uniques":0},{"timestamp":"2025-01-01T01:15:02.918Z","count":0,"uniques":0},{"timestamp":"2025-01-02T01:08:40.661Z","count":0,"uniques":0},{"timestamp":"2025-01-03T01:09:38.510Z","count":0,"uniques":0},{"timestamp":"2025-01-04T01:07:47.420Z","count":0,"uniques":0},{"timestamp":"2025-01-05T01:14:38.768Z","count":0,"uniques":0},{"timestamp":"2025-01-06T01:12:41.968Z","count":0,"uniques":0},{"timestamp":"2025-01-07T01:09:45.469Z","count":0,"uniques":0},{"timestamp":"2025-01-08T01:09:38.356Z","count":0,"uniques":0},{"timestamp":"2025-01-09T01:09:14.392Z","count":0,"uniques":0},{"timestamp":"2025-01-10T01:11:16.662Z","count":0,"uniques":0},{"timestamp":"2025-01-11T01:09:48.429Z","count":0,"uniques":0},{"timestamp":"2025-01-12T01:16:01.034Z","count":0,"uniques":0},{"timestamp":"2025-01-13T01:13:12.183Z","count":0,"uniques":0},{"timestamp":"2025-01-14T00:00:00.000Z","count":1,"uniques":1},{"timestamp":"2025-01-15T01:07:57.813Z","count":0,"uniques":0},{"timestamp":"2025-01-16T01:07:15.306Z","count":0,"uniques":0},{"timestamp":"2025-01-17T01:07:03.201Z","count":0,"uniques":0},{"timestamp":"2025-01-18T01:05:24.012Z","count":0,"uniques":0},{"timestamp":"2025-01-19T01:12:37.511Z","count":0,"uniques":0},{"timestamp":"2025-01-20T01:08:38.459Z","count":0,"uniques":0},{"timestamp":"2025-01-21T01:07:00.571Z","count":0,"uniques":0},{"timestamp":"2025-01-22T01:09:13.727Z","count":0,"uniques":0},{"timestamp":"2025-01-23T01:07:42.092Z","count":0,"uniques":0},{"timestamp":"2025-01-24T01:07:45.378Z","count":0,"uniques":0},{"timestamp":"2025-01-25T01:04:11.283Z","count":0,"uniques":0},{"timestamp":"2025-01-26T01:09:56.908Z","count":0,"uniques":0},{"timestamp":"2025-01-27T01:08:56.527Z","count":0,"uniques":0},{"timestamp":"2025-01-28T01:07:30.919Z","count":0,"uniques":0},{"timestamp":"2025-01-29T01:07:28.641Z","count":0,"uniques":0},{"timestamp":"2025-01-30T01:06:25.553Z","count":0,"uniques":0},{"timestamp":"2025-01-31T01:07:47.941Z","count":0,"uniques":0},{"timestamp":"2025-02-01T01:11:37.448Z","count":0,"uniques":0},{"timestamp":"2025-02-02T01:11:10.571Z","count":0,"uniques":0},{"timestamp":"2025-02-03T01:08:54.788Z","count":0,"uniques":0},{"timestamp":"2025-02-04T01:07:53.858Z","count":0,"uniques":0},{"timestamp":"2025-02-05T01:08:45.628Z","count":0,"uniques":0},{"timestamp":"2025-02-06T01:08:49.994Z","count":0,"uniques":0},{"timestamp":"2025-02-07T01:09:01.762Z","count":0,"uniques":0},{"timestamp":"2025-02-08T01:06:49.214Z","count":0,"uniques":0},{"timestamp":"2025-02-09T01:12:28.377Z","count":0,"uniques":0},{"timestamp":"2025-02-10T01:10:05.399Z","count":0,"uniques":0},{"timestamp":"2025-02-11T01:08:36.331Z","count":0,"uniques":0},{"timestamp":"2025-02-12T01:08:52.203Z","count":0,"uniques":0},{"timestamp":"2025-02-13T01:09:19.230Z","count":0,"uniques":0},{"timestamp":"2025-02-14T01:09:07.466Z","count":0,"uniques":0},{"timestamp":"2025-02-15T01:08:02.905Z","count":0,"uniques":0},{"timestamp":"2025-02-16T01:14:33.318Z","count":0,"uniques":0},{"timestamp":"2025-02-17T01:11:53.341Z","count":0,"uniques":0},{"timestamp":"2025-02-18T01:09:12.917Z","count":0,"uniques":0},{"timestamp":"2025-02-19T01:09:34.528Z","count":0,"uniques":0},{"timestamp":"2025-02-20T01:09:53.454Z","count":0,"uniques":0},{"timestamp":"2025-02-21T01:10:03.232Z","count":0,"uniques":0},{"timestamp":"2025-02-22T01:07:42.885Z","count":0,"uniques":0},{"timestamp":"2025-02-23T01:14:27.711Z","count":0,"uniques":0},{"timestamp":"2025-02-24T01:12:09.556Z","count":0,"uniques":0},{"timestamp":"2025-02-25T01:11:06.967Z","count":0,"uniques":0},{"timestamp":"2025-02-26T01:10:58.477Z","count":0,"uniques":0},{"timestamp":"2025-02-27T01:11:09.654Z","count":0,"uniques":0},{"timestamp":"2025-02-28T01:11:34.112Z","count":0,"uniques":0},{"timestamp":"2025-03-01T01:15:59.008Z","count":0,"uniques":0},{"timestamp":"2025-03-02T01:15:14.522Z","count":0,"uniques":0},{"timestamp":"2025-03-03T01:13:33.891Z","count":0,"uniques":0},{"timestamp":"2025-03-04T01:12:18.832Z","count":0,"uniques":0},{"timestamp":"2025-03-05T01:12:20.210Z","count":0,"uniques":0},{"timestamp":"2025-03-06T01:12:14.302Z","count":0,"uniques":0},{"timestamp":"2025-03-07T01:12:55.499Z","count":0,"uniques":0},{"timestamp":"2025-03-08T00:57:44.991Z","count":0,"uniques":0},{"timestamp":"2025-03-09T01:02:58.898Z","count":0,"uniques":0},{"timestamp":"2025-03-10T01:01:19.027Z","count":0,"uniques":0},{"timestamp":"2025-03-11T01:12:49.776Z","count":0,"uniques":0},{"timestamp":"2025-03-12T01:12:16.417Z","count":0,"uniques":0},{"timestamp":"2025-03-13T01:13:25.902Z","count":0,"uniques":0},{"timestamp":"2025-03-14T01:12:07.994Z","count":0,"uniques":0},{"timestamp":"2025-03-15T01:11:22.940Z","count":0,"uniques":0},{"timestamp":"2025-03-16T01:17:49.151Z","count":0,"uniques":0},{"timestamp":"2025-03-17T01:15:25.062Z","count":0,"uniques":0},{"timestamp":"2025-03-18T01:13:14.271Z","count":0,"uniques":0},{"timestamp":"2025-03-19T01:13:49.719Z","count":0,"uniques":0},{"timestamp":"2025-03-20T01:12:37.921Z","count":0,"uniques":0},{"timestamp":"2025-03-21T01:14:06.076Z","count":0,"uniques":0},{"timestamp":"2025-03-22T01:12:27.150Z","count":0,"uniques":0},{"timestamp":"2025-03-23T01:18:29.402Z","count":0,"uniques":0},{"timestamp":"2025-03-24T01:16:04.183Z","count":0,"uniques":0},{"timestamp":"2025-03-25T01:14:53.324Z","count":0,"uniques":0},{"timestamp":"2025-03-26T01:14:25.317Z","count":0,"uniques":0},{"timestamp":"2025-03-27T01:13:52.303Z","count":0,"uniques":0},{"timestamp":"2025-03-28T01:13:58.346Z","count":0,"uniques":0},{"timestamp":"2025-03-29T01:13:18.571Z","count":0,"uniques":0},{"timestamp":"2025-03-30T01:19:48.723Z","count":0,"uniques":0},{"timestamp":"2025-03-31T01:18:06.654Z","count":0,"uniques":0},{"timestamp":"2025-04-01T01:23:08.766Z","count":0,"uniques":0},{"timestamp":"2025-04-02T01:15:36.322Z","count":0,"uniques":0},{"timestamp":"2025-04-03T01:14:34.549Z","count":0,"uniques":0},{"timestamp":"2025-04-04T01:14:35.060Z","count":0,"uniques":0},{"timestamp":"2025-04-05T01:13:27.984Z","count":0,"uniques":0},{"timestamp":"2025-04-06T01:19:17.133Z","count":0,"uniques":0},{"timestamp":"2025-04-07T01:17:06.785Z","count":0,"uniques":0},{"timestamp":"2025-04-08T01:15:01.836Z","count":0,"uniques":0},{"timestamp":"2025-04-09T01:15:12.160Z","count":0,"uniques":0},{"timestamp":"2025-04-10T01:15:06.339Z","count":0,"uniques":0},{"timestamp":"2025-04-11T01:15:38.469Z","count":0,"uniques":0},{"timestamp":"2025-04-12T01:14:07.816Z","count":0,"uniques":0},{"timestamp":"2025-04-13T02:42:56.806Z","count":0,"uniques":0},{"timestamp":"2025-04-14T01:18:25.477Z","count":0,"uniques":0},{"timestamp":"2025-04-15T01:17:34.593Z","count":0,"uniques":0},{"timestamp":"2025-04-16T18:22:23.658Z","count":0,"uniques":0},{"timestamp":"2025-04-17T18:22:23.658Z","count":0,"uniques":0},{"timestamp":"2025-04-18T18:22:23.658Z","count":0,"uniques":0},{"timestamp":"2025-04-19T18:22:23.658Z","count":0,"uniques":0},{"timestamp":"2025-04-20T18:22:23.658Z","count":0,"uniques":0},{"timestamp":"2025-04-21T18:22:23.658Z","count":0,"uniques":0},{"timestamp":"2025-04-22T18:22:23.658Z","count":0,"uniques":0},{"timestamp":"2025-04-23T18:22:23.658Z","count":0,"uniques":0},{"timestamp":"2025-04-24T18:22:23.658Z","count":0,"uniques":0},{"timestamp":"2025-04-25T18:22:23.658Z","count":0,"uniques":0},{"timestamp":"2025-04-26T18:22:23.658Z","count":0,"uniques":0},{"timestamp":"2025-04-27T18:22:23.658Z","count":0,"uniques":0},{"timestamp":"2025-04-28T18:22:23.658Z","count":0,"uniques":0},{"timestamp":"2025-04-29T18:22:23.658Z","count":0,"uniques":0},{"timestamp":"2025-04-30T18:22:23.658Z","count":0,"uniques":0},{"timestamp":"2025-05-01T18:22:23.658Z","count":0,"uniques":0},{"timestamp":"2025-05-02T01:17:58.562Z","count":0,"uniques":0},{"timestamp":"2025-05-03T01:16:14.549Z","count":0,"uniques":0},{"timestamp":"2025-05-04T01:25:07.732Z","count":0,"uniques":0},{"timestamp":"2025-05-05T01:21:05.031Z","count":0,"uniques":0},{"timestamp":"2025-05-06T01:18:34.109Z","count":0,"uniques":0},{"timestamp":"2025-05-07T01:18:54.786Z","count":0,"uniques":0},{"timestamp":"2025-05-08T01:19:25.162Z","count":0,"uniques":0},{"timestamp":"2025-05-09T01:18:47.504Z","count":0,"uniques":0},{"timestamp":"2025-05-10T01:16:17.386Z","count":0,"uniques":0},{"timestamp":"2025-05-11T01:23:38.187Z","count":0,"uniques":0},{"timestamp":"2025-05-12T01:21:37.205Z","count":0,"uniques":0},{"timestamp":"2025-05-13T01:20:06.063Z","count":0,"uniques":0},{"timestamp":"2025-05-14T01:18:51.426Z","count":0,"uniques":0},{"timestamp":"2025-05-15T01:17:02.063Z","count":0,"uniques":0},{"timestamp":"2025-05-16T01:20:05.521Z","count":0,"uniques":0},{"timestamp":"2025-05-17T01:18:06.287Z","count":0,"uniques":0},{"timestamp":"2025-05-18T01:24:43.154Z","count":0,"uniques":0},{"timestamp":"2025-05-19T01:23:05.500Z","count":0,"uniques":0},{"timestamp":"2025-05-20T01:20:49.555Z","count":0,"uniques":0},{"timestamp":"2025-05-21T01:20:27.798Z","count":0,"uniques":0},{"timestamp":"2025-05-22T01:19:45.017Z","count":0,"uniques":0},{"timestamp":"2025-05-23T01:19:47.321Z","count":0,"uniques":0},{"timestamp":"2025-05-24T01:17:08.788Z","count":0,"uniques":0},{"timestamp":"2025-05-25T01:26:41.478Z","count":0,"uniques":0},{"timestamp":"2025-05-26T01:21:47.531Z","count":0,"uniques":0},{"timestamp":"2025-05-27T01:19:11.652Z","count":0,"uniques":0},{"timestamp":"2025-05-28T01:20:39.954Z","count":0,"uniques":0},{"timestamp":"2025-05-29T01:20:22.159Z","count":0,"uniques":0},{"timestamp":"2025-05-30T01:18:28.297Z","count":0,"uniques":0},{"timestamp":"2025-05-31T01:18:32.580Z","count":0,"uniques":0},{"timestamp":"2025-06-01T01:43:13.508Z","count":0,"uniques":0},{"timestamp":"2025-06-02T01:23:48.990Z","count":0,"uniques":0},{"timestamp":"2025-06-03T01:21:43.598Z","count":0,"uniques":0},{"timestamp":"2025-06-04T01:21:30.016Z","count":0,"uniques":0},{"timestamp":"2025-06-05T01:20:38.690Z","count":0,"uniques":0},{"timestamp":"2025-06-06T01:20:27.741Z","count":0,"uniques":0},{"timestamp":"2025-06-07T01:19:57.350Z","count":0,"uniques":0},{"timestamp":"2025-06-08T01:28:08.949Z","count":0,"uniques":0},{"timestamp":"2025-06-09T01:25:19.284Z","count":0,"uniques":0},{"timestamp":"2025-06-10T01:22:26.510Z","count":0,"uniques":0},{"timestamp":"2025-06-11T01:22:19.106Z","count":0,"uniques":0},{"timestamp":"2025-06-12T01:20:53.458Z","count":0,"uniques":0},{"timestamp":"2025-06-13T01:22:03.009Z","count":0,"uniques":0},{"timestamp":"2025-06-14T01:19:07.974Z","count":0,"uniques":0},{"timestamp":"2025-06-15T01:38:01.348Z","count":0,"uniques":0},{"timestamp":"2025-06-16T01:24:23.015Z","count":0,"uniques":0},{"timestamp":"2025-06-17T01:22:20.717Z","count":0,"uniques":0},{"timestamp":"2025-06-18T01:21:35.785Z","count":0,"uniques":0},{"timestamp":"2025-06-19T01:22:11.724Z","count":0,"uniques":0},{"timestamp":"2025-06-20T01:21:29.228Z","count":0,"uniques":0},{"timestamp":"2025-06-21T01:20:40.831Z","count":0,"uniques":0}]
