[{"timestamp":"2026-07-08T02:26:53.085Z","count":0,"uniques":0},{"timestamp":"2026-07-09T02:42:23.625Z","count":0,"uniques":0},{"timestamp":"2026-07-10T02:45:31.481Z","count":0,"uniques":0},{"timestamp":"2026-07-11T02:24:45.117Z","count":0,"uniques":0},{"timestamp":"2026-07-12T02:29:43.219Z","count":0,"uniques":0},{"timestamp":"2026-07-13T02:31:28.995Z","count":0,"uniques":0},{"timestamp":"2026-07-14T02:10:44.553Z","count":0,"uniques":0},{"timestamp":"2026-07-15T02:08:36.659Z","count":0,"uniques":0}]
